odoo/addons/account_payment_multi_deduction_activity/README.rst
odoo/addons/account_payment_multi_deduction_activity/__init__.py
odoo/addons/account_payment_multi_deduction_activity/__manifest__.py
odoo/addons/account_payment_multi_deduction_activity/readme/CONTRIBUTORS.md
odoo/addons/account_payment_multi_deduction_activity/readme/DESCRIPTION.md
odoo/addons/account_payment_multi_deduction_activity/static/description/icon.png
odoo/addons/account_payment_multi_deduction_activity/static/description/index.html
odoo/addons/account_payment_multi_deduction_activity/tests/__init__.py
odoo/addons/account_payment_multi_deduction_activity/tests/test_payment_multi_deduction_activity.py
odoo/addons/account_payment_multi_deduction_activity/wizard/__init__.py
odoo/addons/account_payment_multi_deduction_activity/wizard/account_payment_deduction.py
odoo/addons/account_payment_multi_deduction_activity/wizard/account_payment_register.py
odoo/addons/account_payment_multi_deduction_activity/wizard/account_payment_register_views.xml
odoo_addon_account_payment_multi_deduction_activity-18.0.1.0.0.1.dist-info/METADATA
odoo_addon_account_payment_multi_deduction_activity-18.0.1.0.0.1.dist-info/WHEEL
odoo_addon_account_payment_multi_deduction_activity-18.0.1.0.0.1.dist-info/top_level.txt
odoo_addon_account_payment_multi_deduction_activity-18.0.1.0.0.1.dist-info/RECORD
